setup.py
uarray.py
pycopy_cpython_uarray.egg-info/PKG-INFO
pycopy_cpython_uarray.egg-info/SOURCES.txt
pycopy_cpython_uarray.egg-info/dependency_links.txt
pycopy_cpython_uarray.egg-info/top_level.txt